wellfrei/__init__.py
wellfrei/core.py
wellfrei/utils.py
wellfrei-0.1.6.dist-info/METADATA
wellfrei-0.1.6.dist-info/WHEEL
wellfrei-0.1.6.dist-info/top_level.txt
wellfrei-0.1.6.dist-info/RECORD
