Metadata-Version: 2.4
Name: wellfrei
Version: 0.1.6
Summary: Scientific algorithm developed by the Wellfrei research group
Author: Wellfrei Research Group
Classifier: Intended Audience :: Science/Research
Classifier: Topic :: Scientific/Engineering
Classifier: Programming Language :: Python :: 3
Requires-Python: >=3.8
Requires-Dist: numpy>=1.20
